topogen/__init__.py
topogen/colorlog.py
topogen/config.py
topogen/dnshost.py
topogen/lxcfrr.py
topogen/main.py
topogen/models.py
topogen/render.py
topogen/templates/__init__.py
topogen/templates/iol-xe.jinja2
topogen/templates/iosv.jinja2
topogen/templates/lxc.jinja2
topogen-0.2.2.dist-info/METADATA
topogen-0.2.2.dist-info/WHEEL
topogen-0.2.2.dist-info/entry_points.txt
topogen-0.2.2.dist-info/licenses/LICENSE
topogen-0.2.2.dist-info/RECORD
