Metadata-Version: 2.4
Name: topogen
Version: 0.2.2
Summary: Generate test topology files and configurations for CML2
Project-URL: Homepage, https://developer.cisco.com/modeling-labs
Project-URL: Repository, https://github.com/rschmied/topogen
Project-URL: Issues, https://github.com/rschmied/topogen/issues
Project-URL: Changelog, https://github.com/crschmied/topogen/blob/master/CHANGELOG.md
Author-email: Ralph Schmieder <rschmied@cisco.com>
License: MIT
License-File: LICENSE
Keywords: automation,network-programming,simulation,tools,virtualization
Classifier: Development Status :: 4 - Beta
Classifier: Environment :: Console
Classifier: Intended Audience :: Telecommunications Industry
Classifier: License :: OSI Approved :: MIT License
Classifier: Operating System :: OS Independent
Classifier: Programming Language :: Python :: 3
Classifier: Programming Language :: Python :: 3.9
Classifier: Programming Language :: Python :: 3.10
Classifier: Programming Language :: Python :: 3.11
Classifier: Programming Language :: Python :: 3.12
Classifier: Topic :: Internet
Requires-Python: >=3.12
Requires-Dist: enlighten>=1
Requires-Dist: jinja2>=3
Requires-Dist: networkx>=3
Requires-Dist: pyserde[toml]>=0.22.2
Requires-Dist: virl2-client>=2.7.0
Provides-Extra: all
Requires-Dist: numpy>=2.2.0; extra == 'all'
Requires-Dist: scipy>=1.14.1; extra == 'all'
